uwgs/__init__.py
uwgs/client.py
uwgs/group.py
uwgs/membership.py
uwgs/search.py
uwgs/types.py
uwgs-0.2.0.dist-info/LICENSE
uwgs-0.2.0.dist-info/METADATA
uwgs-0.2.0.dist-info/WHEEL
uwgs-0.2.0.dist-info/top_level.txt
uwgs-0.2.0.dist-info/RECORD
