Metadata-Version: 2.1
Name: uwgs
Version: 0.2.0
Summary: Flexible http client for reading UW Groups API v3.
Home-page: https://github.com/uwrit/uwgs
Author: UW Medicine Research IT
License: UNKNOWN
Platform: UNKNOWN
Classifier: Programming Language :: Python :: 3
Classifier: License :: OSI Approved :: BSD License
Classifier: Operating System :: OS Independent
